{
    "animations": {
        "animation.skeleguard.attack": {
            "bones": {
                "right_arm": {
                    "rotation": {
                        "0.0": {
                            "lerp_mode": "catmullrom",
                            "post": [
                                0,
                                0,
                                0
                            ]
                        },
                        "0.1": {
                            "lerp_mode": "catmullrom",
                            "post": [
                                -11.87707,
                                12.65884,
                                46.17791
                            ]
                        },
                        "0.5": {
                            "lerp_mode": "catmullrom",
                            "post": [
                                -135,
                                0,
                                0
                            ]
                        },
                        "0.75": {
                            "lerp_mode": "catmullrom",
                            "post": [
                                -44.00703,
                                -10.54529,
                                -10.72858
                            ]
                        }
                    }
                }
            },
            "loop": true
        },
        "animation.skeleguard.move": {
            "bones": {
                "body": {
                    "rotation": [
                        "(math.cos(query.life_time * -360.0) * 9.0) * 0.75",
                        "(2.0 + math.cos((0 * 2 + query.life_time * 20.0) * 14.32)) * 0.75",
                        "(math.sin(query.life_time * -360.0) * 9.0) * 0.75"
                    ]
                },
                "left_arm": {
                    "rotation": [
                        "variable.tcos0 * 1.2",
                        0,
                        0
                    ]
                },
                "left_leg": {
                    "rotation": [
                        "variable.tcos0 * -1.2",
                        0,
                        0
                    ]
                },
                "right_arm": {
                    "rotation": [
                        "variable.tcos0 * -1.2",
                        0,
                        0
                    ]
                },
                "right_leg": {
                    "rotation": [
                        "variable.tcos0 * 1.2",
                        0,
                        0
                    ]
                }
            },
            "loop": true
        }
    },
    "format_version": "1.8.0"
}